{
  "categories": ["청소년", "성인"],
  "청소년": {
    "description": "청소년기는 성장판이 닫히기 전으로, 근육의 발달보다는 올바른 자세, 협응력, 심폐지구력 향상이 중요합니다.",
    "training_focus": ["전신 협응력", "코어 안정성", "유연성", "기초 근지구력"],
    "운동부하": {
      "강도": "1RM의 50~60%",
      "횟수": "12~15회",
      "세트": "2~3세트",
      "빈도": "주 3회 이하"
    },
    "운동유형": {
      "전신": ["버피 테스트", "점핑잭", "플랭크", "마운틴 클라이머"],
      "상체": ["푸쉬업(무릎)", "밴드 로우", "숄더 탭", "플랭크 숄더터치"],
      "하체": ["스쿼트", "런지", "사이드 스텝", "힙브릿지"],
      "코어": ["플랭크", "데드버그", "버드독", "러시안 트위스트"]
    },
    "주의사항": [
      "무리한 중량보다는 정확한 자세가 우선",
      "성장판 손상을 방지하기 위해 중량 훈련은 제한",
      "유산소 + 근력운동을 병행하여 전신 조화 발달 유도"
    ]
  },
  "성인": {
    "description": "성인은 근육 발달과 체력 향상이 가능하므로, 점진적 과부하 원칙에 따라 체계적인 근력 훈련이 필요합니다.",
    "training_focus": ["근비대", "근지구력", "심폐지구력", "체지방 감량"],
    "운동부하": {
      "강도": "1RM의 65~85%",
      "횟수": "8~12회",
      "세트": "3~5세트",
      "빈도": "주 3~5회"
    },
    "운동유형": {
      "전신": ["스쿼트 + 프레스", "버피", "마운틴 클라이머", "데드리프트"],
      "상체": ["벤치프레스", "랫풀다운", "덤벨 숄더프레스", "바벨 로우"],
      "하체": ["바벨 스쿼트", "런지", "레그프레스", "카프레이즈"],
      "코어": ["크런치", "레그레이즈", "플랭크", "사이드 브릿지"]
    },
    "주의사항": [
      "운동 전후 충분한 스트레칭으로 부상 예방",
      "중량은 체력 수준에 따라 점진적으로 증가",
      "과도한 중량보다는 자세 정확도 우선",
      "3대 운동(스쿼트, 벤치프레스, 데드리프트)은 트레이너 지도 하에 수행 권장"
    ]
  }
}
